penn/__init__.py
penn/__main__.py
penn/convert.py
penn/core.py
penn/decode.py
penn/load.py
penn/periodicity.py
penn/voicing.py
penn/assets/partitions/mdb.json
penn/assets/partitions/ptdb.json
penn/config/__init__.py
penn/config/defaults.py
penn/config/static.py
penn/data/__init__.py
penn/data/dataset.py
penn/data/loader.py
penn/data/sampler.py
penn/data/download/__init__.py
penn/data/download/__main__.py
penn/data/download/core.py
penn/data/preprocess/__init__.py
penn/data/preprocess/__main__.py
penn/data/preprocess/core.py
penn/dsp/__init__.py
penn/dsp/dio.py
penn/dsp/pyin.py
penn/evaluate/__init__.py
penn/evaluate/__main__.py
penn/evaluate/core.py
penn/evaluate/metrics.py
penn/model/__init__.py
penn/model/core.py
penn/model/crepe.py
penn/model/deepf0.py
penn/model/fcnf0.py
penn/partition/__init__.py
penn/partition/__main__.py
penn/partition/core.py
penn/plot/__init__.py
penn/plot/density/__init__.py
penn/plot/density/__main__.py
penn/plot/density/core.py
penn/plot/logits/__init__.py
penn/plot/logits/__main__.py
penn/plot/logits/core.py
penn/plot/threshold/__init__.py
penn/plot/threshold/__main__.py
penn/plot/threshold/core.py
penn/train/__init__.py
penn/train/__main__.py
penn/train/core.py
penn-0.0.14.dist-info/LICENSE
penn-0.0.14.dist-info/METADATA
penn-0.0.14.dist-info/WHEEL
penn-0.0.14.dist-info/top_level.txt
penn-0.0.14.dist-info/RECORD
