Metadata-Version: 2.1
Name: penn
Version: 0.0.14
Summary: Pitch Estimating Neural Networks (PENN)
Home-page: https://github.com/interactiveaudiolab/penn
Author: Max Morrison, Caedon Hsieh, Nathan Pruyne, and Bryan Pardo
Author-email: interactiveaudiolab@gmail.com
License: MIT
Keywords: audio,frequency,music,periodicity,pitch,speech
Classifier: License :: OSI Approved :: MIT License
License-File: LICENSE
Requires-Dist: huggingface-hub
Requires-Dist: numpy
Requires-Dist: torch
Requires-Dist: torchaudio
Requires-Dist: torchutil
Requires-Dist: yapecs
Provides-Extra: test
Requires-Dist: librosa ; extra == 'test'
Requires-Dist: pytest ; extra == 'test'
Provides-Extra: train
Requires-Dist: librosa ; extra == 'train'
Requires-Dist: matplotlib ; extra == 'train'
Requires-Dist: pyworld ; extra == 'train'
Requires-Dist: scipy ; extra == 'train'
Requires-Dist: torchcrepe ; extra == 'train'
